src/__init__.py
src/cli_interface.py
src/main.py
src/core/__init__.py
src/core/bt_file.py
src/core/bt_graph.py
src/core/bt_module.py
src/plantuml/__init__.py
src/plantuml/fetch_git.py
src/plantuml/plantuml_file_creator.py
src/plantumlv2/__init__.py
src/plantumlv2/pu_entities.py
src/plantumlv2/pu_manager.py
src/plantumlv2/utils.py
src/utils/__init__.py
src/utils/config_manager_singleton.py
src/utils/functions.py
src/utils/path_manager_singleton.py
MT_diagrams-0.2.0.dist-info/METADATA
MT_diagrams-0.2.0.dist-info/WHEEL
MT_diagrams-0.2.0.dist-info/entry_points.txt
MT_diagrams-0.2.0.dist-info/top_level.txt
MT_diagrams-0.2.0.dist-info/RECORD
